{
    "listings": [
        {
            "timestamp": "2025-03-01T15:49:26.352Z",
            "pageSize": 48,
            "page": 8,
            "gigId": 200874778,
            "pos": 0,
            "type": "promoted_gigs",
            "is_fiverr_choice": false,
            "seller_name": "wpmaks",
            "seller_country": "TR",
            "seller_level": "top_rated_seller",
            "is_pro": true,
            "buying_review_rating_count": 26,
            "buying_review_rating": 5,
            "price_i": 1500,
            "count": 947,
            "score": 4.9793105,
            "choice_eligibilities": "ALGO_A",
            "listingQuery": "website development"
        },
        {
            "timestamp": "2025-03-01T15:49:26.352Z",
            "pageSize": 48,
            "page": 8,
            "gigId": 178820874,
            "pos": 1,
            "type": "promoted_gigs",
            "is_fiverr_choice": false,
            "seller_name": "zeeshan152",
            "seller_country": "PK",
            "seller_level": "level_two_seller",
            "is_pro": false,
            "buying_review_rating_count": 161,
            "buying_review_rating": 4.7,
            "price_i": 150,
            "count": 456,
            "score": 4.8184395,
            "choice_eligibilities": "ALGO_A",
            "listingQuery": "website development"
        },
        {
            "timestamp": "2025-03-01T15:49:26.352Z",
            "pageSize": 48,
            "page": 8,
            "gigId": 373175690,
            "pos": 2,
            "type": "promoted_gigs",
            "is_fiverr_choice": false,
            "seller_name": "remoove",
            "seller_country": "IT",
            "seller_level": "top_rated_seller",
            "is_pro": true,
            "buying_review_rating_count": 80,
            "buying_review_rating": 5,
            "price_i": 500,
            "count": 89,
            "score": 4.9859157,
            "choice_eligibilities": "ALGO_A",
            "listingQuery": "website development"
        },
        {
            "timestamp": "2025-03-01T15:49:26.352Z",
            "pageSize": 48,
            "page": 8,
            "gigId": 392761714,
            "pos": 3,
            "type": "promoted_gigs",
            "is_fiverr_choice": false,
            "seller_name": "nine_square",
            "seller_country": "IN",
            "seller_level": "top_rated_seller",
            "is_pro": false,
            "buying_review_rating_count": 10,
            "buying_review_rating": 5,
            "price_i": 620,
            "count": 336,
            "score": 4.9658117,
            "choice_eligibilities": "ALGO_A",
            "listingQuery": "website development"
        },
        {
            "timestamp": "2025-03-01T15:49:26.352Z",
            "pageSize": 48,
            "page": 8,
            "gigId": 326285558,
            "pos": 4,
            "type": "normal",
            "is_fiverr_choice": false,
            "seller_name": "wp_arju",
            "seller_country": "BD",
            "seller_level": "level_two_seller",
            "is_pro": false,
            "buying_review_rating_count": 232,
            "buying_review_rating": 4.8,
            "price_i": 80,
            "count": 232,
            "score": 4.81741,
            "choice_eligibilities": "ALGO_A",
            "listingQuery": "website development"
        },
        {
            "timestamp": "2025-03-01T15:49:26.352Z",
            "pageSize": 48,
            "page": 8,
            "gigId": 105353349,
            "pos": 5,
            "type": "normal",
            "is_fiverr_choice": false,
            "seller_name": "m_webs",
            "seller_country": "PK",
            "seller_level": "top_rated_seller",
            "is_pro": false,
            "buying_review_rating_count": 714,
            "buying_review_rating": 5,
            "price_i": 295,
            "count": 729,
            "score": 4.986532,
            "choice_eligibilities": "ALGO_A&ALGO_B",
            "listingQuery": "website development"
        },
        {
            "timestamp": "2025-03-01T15:49:26.352Z",
            "pageSize": 48,
            "page": 8,
            "gigId": 241831050,
            "pos": 6,
            "type": "normal",
            "is_fiverr_choice": false,
            "seller_name": "de_faruque",
            "seller_country": "BD",
            "seller_level": "level_two_seller",
            "is_pro": false,
            "buying_review_rating_count": 147,
            "buying_review_rating": 4.9,
            "price_i": 80,
            "count": 147,
            "score": 4.945652,
            "choice_eligibilities": "ALGO_A",
            "listingQuery": "website development"
        },
        {
            "timestamp": "2025-03-01T15:49:26.352Z",
            "pageSize": 48,
            "page": 8,
            "gigId": 241826421,
            "pos": 7,
            "type": "normal",
            "is_fiverr_choice": false,
            "seller_name": "developer_firoz",
            "seller_country": "BD",
            "seller_level": "level_two_seller",
            "is_pro": false,
            "buying_review_rating_count": 145,
            "buying_review_rating": 4.9,
            "price_i": 40,
            "count": 179,
            "score": 4.918605,
            "choice_eligibilities": "ALGO_A",
            "listingQuery": "website development"
        },
        {
            "timestamp": "2025-03-01T15:49:26.352Z",
            "pageSize": 48,
            "page": 8,
            "gigId": 226417315,
            "pos": 8,
            "type": "normal",
            "is_fiverr_choice": false,
            "seller_name": "alraziq_studios",
            "seller_country": "PK",
            "seller_level": "level_one_seller",
            "is_pro": false,
            "buying_review_rating_count": 227,
            "buying_review_rating": 4.9,
            "price_i": 130,
            "count": 245,
            "score": 4.957227,
            "choice_eligibilities": "ALGO_A",
            "listingQuery": "website development"
        },
        {
            "timestamp": "2025-03-01T15:49:26.352Z",
            "pageSize": 48,
            "page": 8,
            "gigId": 6433801,
            "pos": 9,
            "type": "normal",
            "is_fiverr_choice": false,
            "seller_name": "vinodbansal12",
            "seller_country": "IN",
            "seller_level": "level_two_seller",
            "is_pro": false,
            "buying_review_rating_count": 681,
            "buying_review_rating": 4.9,
            "price_i": 195,
            "count": 1067,
            "score": 4.975815,
            "choice_eligibilities": "ALGO_A",
            "listingQuery": "website development"
        },
        {
            "timestamp": "2025-03-01T15:49:26.352Z",
            "pageSize": 48,
            "page": 8,
            "gigId": 385216880,
            "pos": 10,
            "type": "normal",
            "is_fiverr_choice": false,
            "seller_name": "asmaahad",
            "seller_country": "PK",
            "seller_level": "level_two_seller",
            "is_pro": false,
            "buying_review_rating_count": 10,
            "buying_review_rating": 4.9,
            "price_i": 100,
            "count": 38,
            "score": 5,
            "choice_eligibilities": "ALGO_A",
            "listingQuery": "website development"
        },
        {
            "timestamp": "2025-03-01T15:49:26.352Z",
            "pageSize": 48,
            "page": 8,
            "gigId": 283334178,
            "pos": 11,
            "type": "normal",
            "is_fiverr_choice": false,
            "seller_name": "scared488",
            "seller_country": "PK",
            "seller_level": "level_two_seller",
            "is_pro": false,
            "buying_review_rating_count": 6,
            "buying_review_rating": 4.7,
            "price_i": 80,
            "count": 14,
            "score": 4.75,
            "choice_eligibilities": "ALGO_A",
            "listingQuery": "website development"
        },
        {
            "timestamp": "2025-03-01T15:49:26.352Z",
            "pageSize": 48,
            "page": 8,
            "gigId": 253127057,
            "pos": 12,
            "type": "promoted_gigs",
            "is_fiverr_choice": false,
            "seller_name": "techpulse_",
            "seller_country": "BD",
            "seller_level": "level_two_seller",
            "is_pro": false,
            "buying_review_rating_count": 344,
            "buying_review_rating": 4.8,
            "price_i": 100,
            "count": 344,
            "score": 4.880062,
            "choice_eligibilities": "ALGO_A",
            "listingQuery": "website development"
        },
        {
            "timestamp": "2025-03-01T15:49:26.352Z",
            "pageSize": 48,
            "page": 8,
            "gigId": 356251010,
            "pos": 13,
            "type": "promoted_gigs",
            "is_fiverr_choice": false,
            "seller_name": "wpwizard_",
            "seller_country": "BD",
            "seller_level": "level_two_seller",
            "is_pro": false,
            "buying_review_rating_count": 242,
            "buying_review_rating": 4.9,
            "price_i": 85,
            "count": 242,
            "score": 4.9414415,
            "choice_eligibilities": "ALGO_A",
            "listingQuery": "website development"
        },
        {
            "timestamp": "2025-03-01T15:49:26.352Z",
            "pageSize": 48,
            "page": 8,
            "gigId": 131957053,
            "pos": 14,
            "type": "promoted_gigs",
            "is_fiverr_choice": false,
            "seller_name": "wp_babarali",
            "seller_country": "PK",
            "seller_level": "top_rated_seller",
            "is_pro": false,
            "buying_review_rating_count": 503,
            "buying_review_rating": 4.9,
            "price_i": 700,
            "count": 507,
            "score": 4.9579577,
            "choice_eligibilities": "ALGO_A",
            "listingQuery": "website development"
        },
        {
            "timestamp": "2025-03-01T15:49:26.352Z",
            "pageSize": 48,
            "page": 8,
            "gigId": 154861352,
            "pos": 15,
            "type": "promoted_gigs",
            "is_fiverr_choice": false,
            "seller_name": "wpkashif",
            "seller_country": "PK",
            "seller_level": "level_two_seller",
            "is_pro": false,
            "buying_review_rating_count": 130,
            "buying_review_rating": 4.9,
            "price_i": 125,
            "count": 131,
            "score": 4.9183674,
            "choice_eligibilities": "ALGO_A",
            "listingQuery": "website development"
        },
        {
            "timestamp": "2025-03-01T15:49:26.352Z",
            "pageSize": 48,
            "page": 8,
            "gigId": 240626044,
            "pos": 16,
            "type": "normal",
            "is_fiverr_choice": false,
            "seller_name": "toseeq424",
            "seller_country": "PK",
            "seller_level": "level_two_seller",
            "is_pro": false,
            "buying_review_rating_count": 117,
            "buying_review_rating": 4.9,
            "price_i": 100,
            "count": 150,
            "score": 4.914815,
            "choice_eligibilities": "ALGO_A",
            "listingQuery": "website development"
        },
        {
            "timestamp": "2025-03-01T15:49:26.352Z",
            "pageSize": 48,
            "page": 8,
            "gigId": 395123916,
            "pos": 17,
            "type": "normal",
            "is_fiverr_choice": false,
            "seller_name": "haroon_shah",
            "seller_country": "PK",
            "seller_level": "level_two_seller",
            "is_pro": false,
            "buying_review_rating_count": 134,
            "buying_review_rating": 4.9,
            "price_i": 100,
            "count": 152,
            "score": 4.919094,
            "choice_eligibilities": "ALGO_A",
            "listingQuery": "website development"
        },
        {
            "timestamp": "2025-03-01T15:49:26.352Z",
            "pageSize": 48,
            "page": 8,
            "gigId": 381346915,
            "pos": 18,
            "type": "normal",
            "is_fiverr_choice": false,
            "seller_name": "abrar_90",
            "seller_country": "PK",
            "seller_level": "level_two_seller",
            "is_pro": false,
            "buying_review_rating_count": 38,
            "buying_review_rating": 5,
            "price_i": 60,
            "count": 41,
            "score": 5,
            "choice_eligibilities": "ALGO_A",
            "listingQuery": "website development"
        },
        {
            "timestamp": "2025-03-01T15:49:26.352Z",
            "pageSize": 48,
            "page": 8,
            "gigId": 117472133,
            "pos": 19,
            "type": "normal",
            "is_fiverr_choice": false,
            "seller_name": "azeem_saleem",
            "seller_country": "PK",
            "seller_level": "top_rated_seller",
            "is_pro": true,
            "buying_review_rating_count": 550,
            "buying_review_rating": 4.9,
            "price_i": 295,
            "count": 615,
            "score": 4.8967137,
            "choice_eligibilities": "ALGO_A",
            "listingQuery": "website development"
        },
        {
            "timestamp": "2025-03-01T15:49:26.352Z",
            "pageSize": 48,
            "page": 8,
            "gigId": 378711420,
            "pos": 20,
            "type": "normal",
            "is_fiverr_choice": false,
            "seller_name": "blockweb",
            "seller_country": "IN",
            "seller_level": "level_two_seller",
            "is_pro": false,
            "buying_review_rating_count": 11,
            "buying_review_rating": 5,
            "price_i": 100,
            "count": 27,
            "score": 4.977778,
            "choice_eligibilities": "ALGO_A",
            "listingQuery": "website development"
        },
        {
            "timestamp": "2025-03-01T15:49:26.352Z",
            "pageSize": 48,
            "page": 8,
            "gigId": 370764787,
            "pos": 21,
            "type": "normal",
            "is_fiverr_choice": false,
            "seller_name": "web_genius02",
            "seller_country": "BD",
            "seller_level": "level_two_seller",
            "is_pro": false,
            "buying_review_rating_count": 165,
            "buying_review_rating": 4.9,
            "price_i": 80,
            "count": 165,
            "score": 4.905797,
            "choice_eligibilities": "ALGO_A",
            "listingQuery": "website development"
        },
        {
            "timestamp": "2025-03-01T15:49:26.352Z",
            "pageSize": 48,
            "page": 8,
            "gigId": 264406915,
            "pos": 22,
            "type": "normal",
            "is_fiverr_choice": false,
            "seller_name": "massivework",
            "seller_country": "IN",
            "seller_level": "top_rated_seller",
            "is_pro": true,
            "buying_review_rating_count": 369,
            "buying_review_rating": 4.9,
            "price_i": 475,
            "count": 1858,
            "score": 4.94754,
            "choice_eligibilities": "ALGO_A",
            "listingQuery": "website development"
        },
        {
            "timestamp": "2025-03-01T15:49:26.352Z",
            "pageSize": 48,
            "page": 8,
            "gigId": 390323519,
            "pos": 23,
            "type": "normal",
            "is_fiverr_choice": false,
            "seller_name": "solution_sqd",
            "seller_country": "BD",
            "seller_level": "level_two_seller",
            "is_pro": false,
            "buying_review_rating_count": 123,
            "buying_review_rating": 5,
            "price_i": 80,
            "count": 124,
            "score": 4.9811826,
            "choice_eligibilities": "ALGO_A",
            "listingQuery": "website development"
        },
        {
            "timestamp": "2025-03-01T15:49:26.352Z",
            "pageSize": 48,
            "page": 8,
            "gigId": 375053244,
            "pos": 24,
            "type": "promoted_gigs",
            "is_fiverr_choice": false,
            "seller_name": "talhaumair_",
            "seller_country": "PK",
            "seller_level": "level_one_seller",
            "is_pro": false,
            "buying_review_rating_count": 17,
            "buying_review_rating": 5,
            "price_i": 90,
            "count": 17,
            "score": 5,
            "choice_eligibilities": "ALGO_A",
            "listingQuery": "website development"
        },
        {
            "timestamp": "2025-03-01T15:49:26.352Z",
            "pageSize": 48,
            "page": 8,
            "gigId": 194856189,
            "pos": 25,
            "type": "promoted_gigs",
            "is_fiverr_choice": false,
            "seller_name": "jamesbns",
            "seller_country": "AE",
            "seller_level": "level_two_seller",
            "is_pro": true,
            "buying_review_rating_count": 42,
            "buying_review_rating": 5,
            "price_i": 1995,
            "count": 66,
            "score": 4.99187,
            "choice_eligibilities": "ALGO_A",
            "listingQuery": "website development"
        },
        {
            "timestamp": "2025-03-01T15:49:26.352Z",
            "pageSize": 48,
            "page": 8,
            "gigId": 348289424,
            "pos": 26,
            "type": "promoted_gigs",
            "is_fiverr_choice": false,
            "seller_name": "minahil_ashfaq",
            "seller_country": "PK",
            "seller_level": "level_two_seller",
            "is_pro": false,
            "buying_review_rating_count": 53,
            "buying_review_rating": 4.9,
            "price_i": 80,
            "count": 69,
            "score": 4.8416667,
            "choice_eligibilities": "ALGO_A",
            "listingQuery": "website development"
        },
        {
            "timestamp": "2025-03-01T15:49:26.352Z",
            "pageSize": 48,
            "page": 8,
            "gigId": 189574944,
            "pos": 27,
            "type": "promoted_gigs",
            "is_fiverr_choice": false,
            "seller_name": "qasimkhan929",
            "seller_country": "PK",
            "seller_level": "level_two_seller",
            "is_pro": false,
            "buying_review_rating_count": 101,
            "buying_review_rating": 4.9,
            "price_i": 80,
            "count": 103,
            "score": 4.935185,
            "choice_eligibilities": "ALGO_A",
            "listingQuery": "website development"
        },
        {
            "timestamp": "2025-03-01T15:49:26.352Z",
            "pageSize": 48,
            "page": 8,
            "gigId": 385566607,
            "pos": 28,
            "type": "normal",
            "is_fiverr_choice": false,
            "seller_name": "salehin7100",
            "seller_country": "BD",
            "seller_level": "level_one_seller",
            "is_pro": false,
            "buying_review_rating_count": 18,
            "buying_review_rating": 4.7,
            "price_i": 80,
            "count": 24,
            "score": 4.766667,
            "choice_eligibilities": "ALGO_A",
            "listingQuery": "website development"
        },
        {
            "timestamp": "2025-03-01T15:49:26.352Z",
            "pageSize": 48,
            "page": 8,
            "gigId": 211339949,
            "pos": 29,
            "type": "normal",
            "is_fiverr_choice": false,
            "seller_name": "shaamim_",
            "seller_country": "BD",
            "seller_level": "top_rated_seller",
            "is_pro": false,
            "buying_review_rating_count": 382,
            "buying_review_rating": 5,
            "price_i": 95,
            "count": 385,
            "score": 4.986607,
            "choice_eligibilities": "ALGO_A",
            "listingQuery": "website development"
        },
        {
            "timestamp": "2025-03-01T15:49:26.352Z",
            "pageSize": 48,
            "page": 8,
            "gigId": 33403045,
            "pos": 30,
            "type": "normal",
            "is_fiverr_choice": false,
            "seller_name": "bhashkar007",
            "seller_country": "IN",
            "seller_level": "level_one_seller",
            "is_pro": false,
            "buying_review_rating_count": 11,
            "buying_review_rating": 5,
            "price_i": 100,
            "count": 116,
            "score": 4.82243,
            "choice_eligibilities": "ALGO_A",
            "listingQuery": "website development"
        },
        {
            "timestamp": "2025-03-01T15:49:26.352Z",
            "pageSize": 48,
            "page": 8,
            "gigId": 373881013,
            "pos": 31,
            "type": "normal",
            "is_fiverr_choice": false,
            "seller_name": "dev_umen",
            "seller_country": "PK",
            "seller_level": "level_two_seller",
            "is_pro": false,
            "buying_review_rating_count": 98,
            "buying_review_rating": 4.9,
            "price_i": 20,
            "count": 98,
            "score": 5,
            "choice_eligibilities": "ALGO_A",
            "listingQuery": "website development"
        },
        {
            "timestamp": "2025-03-01T15:49:26.352Z",
            "pageSize": 48,
            "page": 8,
            "gigId": 354433272,
            "pos": 32,
            "type": "normal",
            "is_fiverr_choice": false,
            "seller_name": "wix_buddy",
            "seller_country": "BD",
            "seller_level": "level_two_seller",
            "is_pro": true,
            "buying_review_rating_count": 575,
            "buying_review_rating": 4.8,
            "price_i": 550,
            "count": 579,
            "score": 4.8874893,
            "choice_eligibilities": "ALGO_A",
            "listingQuery": "website development"
        },
        {
            "timestamp": "2025-03-01T15:49:26.352Z",
            "pageSize": 48,
            "page": 8,
            "gigId": 374755433,
            "pos": 33,
            "type": "normal",
            "is_fiverr_choice": false,
            "seller_name": "basit53",
            "seller_country": "PK",
            "seller_level": "level_two_seller",
            "is_pro": false,
            "buying_review_rating_count": 50,
            "buying_review_rating": 4.9,
            "price_i": 30,
            "count": 101,
            "score": 5,
            "choice_eligibilities": "ALGO_A",
            "listingQuery": "website development"
        },
        {
            "timestamp": "2025-03-01T15:49:26.352Z",
            "pageSize": 48,
            "page": 8,
            "gigId": 346452795,
            "pos": 34,
            "type": "normal",
            "is_fiverr_choice": false,
            "seller_name": "waleedbinkha656",
            "seller_country": "PK",
            "seller_level": "level_two_seller",
            "is_pro": false,
            "buying_review_rating_count": 287,
            "buying_review_rating": 4.9,
            "price_i": 80,
            "count": 287,
            "score": 4.9535356,
            "choice_eligibilities": "ALGO_A",
            "listingQuery": "website development"
        },
        {
            "timestamp": "2025-03-01T15:49:26.352Z",
            "pageSize": 48,
            "page": 8,
            "gigId": 382027299,
            "pos": 35,
            "type": "normal",
            "is_fiverr_choice": false,
            "seller_name": "sams_web2",
            "seller_country": "PK",
            "seller_level": "level_two_seller",
            "is_pro": false,
            "buying_review_rating_count": 28,
            "buying_review_rating": 4.9,
            "price_i": 85,
            "count": 28,
            "score": 5,
            "choice_eligibilities": "ALGO_A",
            "listingQuery": "website development"
        },
        {
            "timestamp": "2025-03-01T15:49:26.352Z",
            "pageSize": 48,
            "page": 8,
            "gigId": 362116972,
            "pos": 36,
            "type": "promoted_gigs",
            "is_fiverr_choice": false,
            "seller_name": "threepixl",
            "seller_country": "DE",
            "seller_level": "level_two_seller",
            "is_pro": true,
            "buying_review_rating_count": 101,
            "buying_review_rating": 4.9,
            "price_i": 550,
            "count": 101,
            "score": 4.8819447,
            "choice_eligibilities": "ALGO_A",
            "listingQuery": "website development"
        },
        {
            "timestamp": "2025-03-01T15:49:26.352Z",
            "pageSize": 48,
            "page": 8,
            "gigId": 117985210,
            "pos": 37,
            "type": "promoted_gigs",
            "is_fiverr_choice": false,
            "seller_name": "iamarifcom",
            "seller_country": "TR",
            "seller_level": "top_rated_seller",
            "is_pro": true,
            "buying_review_rating_count": 189,
            "buying_review_rating": 4.8,
            "price_i": 750,
            "count": 189,
            "score": 4.869963,
            "choice_eligibilities": "ALGO_A",
            "listingQuery": "website development"
        },
        {
            "timestamp": "2025-03-01T15:49:26.352Z",
            "pageSize": 48,
            "page": 8,
            "gigId": 374484734,
            "pos": 38,
            "type": "promoted_gigs",
            "is_fiverr_choice": false,
            "seller_name": "shrawaan",
            "seller_country": "IN",
            "seller_level": "level_two_seller",
            "is_pro": false,
            "buying_review_rating_count": 24,
            "buying_review_rating": 5,
            "price_i": 80,
            "count": 24,
            "score": 5,
            "choice_eligibilities": "ALGO_A",
            "listingQuery": "website development"
        },
        {
            "timestamp": "2025-03-01T15:49:26.352Z",
            "pageSize": 48,
            "page": 8,
            "gigId": 158252719,
            "pos": 39,
            "type": "promoted_gigs",
            "is_fiverr_choice": false,
            "seller_name": "ubaidqamar81",
            "seller_country": "AU",
            "seller_level": "level_two_seller",
            "is_pro": false,
            "buying_review_rating_count": 308,
            "buying_review_rating": 4.9,
            "price_i": 65,
            "count": 357,
            "score": 4.8919754,
            "choice_eligibilities": "ALGO_A",
            "listingQuery": "website development"
        },
        {
            "timestamp": "2025-03-01T15:49:26.352Z",
            "pageSize": 48,
            "page": 8,
            "gigId": 331249830,
            "pos": 40,
            "type": "normal",
            "is_fiverr_choice": false,
            "seller_name": "hira_wpdev",
            "seller_country": "PK",
            "seller_level": "level_two_seller",
            "is_pro": false,
            "buying_review_rating_count": 93,
            "buying_review_rating": 4.8,
            "price_i": 80,
            "count": 93,
            "score": 4.7058825,
            "choice_eligibilities": "ALGO_A",
            "listingQuery": "website development"
        },
        {
            "timestamp": "2025-03-01T15:49:26.352Z",
            "pageSize": 48,
            "page": 8,
            "gigId": 276844933,
            "pos": 41,
            "type": "normal",
            "is_fiverr_choice": false,
            "seller_name": "chabdullah07",
            "seller_country": "PK",
            "seller_level": "level_two_seller",
            "is_pro": false,
            "buying_review_rating_count": 423,
            "buying_review_rating": 5,
            "price_i": 85,
            "count": 433,
            "score": 4.9528456,
            "choice_eligibilities": "ALGO_A",
            "listingQuery": "website development"
        },
        {
            "timestamp": "2025-03-01T15:49:26.352Z",
            "pageSize": 48,
            "page": 8,
            "gigId": 124337138,
            "pos": 42,
            "type": "normal",
            "is_fiverr_choice": false,
            "seller_name": "developeratbest",
            "seller_country": "PK",
            "seller_level": "top_rated_seller",
            "is_pro": false,
            "buying_review_rating_count": 368,
            "buying_review_rating": 4.9,
            "price_i": 95,
            "count": 382,
            "score": 4.924051,
            "choice_eligibilities": "ALGO_A",
            "listingQuery": "website development"
        },
        {
            "timestamp": "2025-03-01T15:49:26.352Z",
            "pageSize": 48,
            "page": 8,
            "gigId": 33928190,
            "pos": 43,
            "type": "normal",
            "is_fiverr_choice": false,
            "seller_name": "faizan6089",
            "seller_country": "PK",
            "seller_level": "level_two_seller",
            "is_pro": false,
            "buying_review_rating_count": 321,
            "buying_review_rating": 4.9,
            "price_i": 80,
            "count": 471,
            "score": 4.945513,
            "choice_eligibilities": "ALGO_A",
            "listingQuery": "website development"
        },
        {
            "timestamp": "2025-03-01T15:49:26.352Z",
            "pageSize": 48,
            "page": 8,
            "gigId": 206070461,
            "pos": 44,
            "type": "promoted_gigs",
            "is_fiverr_choice": false,
            "seller_name": "abubakar52021",
            "seller_country": "PK",
            "seller_level": "level_two_seller",
            "is_pro": false,
            "buying_review_rating_count": 103,
            "buying_review_rating": 5,
            "price_i": 30,
            "count": 124,
            "score": 4.9911504,
            "choice_eligibilities": "ALGO_A",
            "listingQuery": "website development"
        },
        {
            "timestamp": "2025-03-01T15:49:26.352Z",
            "pageSize": 48,
            "page": 8,
            "gigId": 374839520,
            "pos": 45,
            "type": "promoted_gigs",
            "is_fiverr_choice": false,
            "seller_name": "shahmirnawaz787",
            "seller_country": "PK",
            "seller_level": "level_two_seller",
            "is_pro": false,
            "buying_review_rating_count": 40,
            "buying_review_rating": 4.9,
            "price_i": 95,
            "count": 40,
            "score": 4.977778,
            "choice_eligibilities": "ALGO_A",
            "listingQuery": "website development"
        },
        {
            "timestamp": "2025-03-01T15:49:26.352Z",
            "pageSize": 48,
            "page": 8,
            "gigId": 387058361,
            "pos": 46,
            "type": "promoted_gigs",
            "is_fiverr_choice": false,
            "seller_name": "landing_page_pr",
            "seller_country": "BD",
            "seller_level": "level_two_seller",
            "is_pro": false,
            "buying_review_rating_count": 141,
            "buying_review_rating": 4.9,
            "price_i": 85,
            "count": 141,
            "score": 4.9314423,
            "choice_eligibilities": "ALGO_A",
            "listingQuery": "website development"
        },
        {
            "timestamp": "2025-03-01T15:49:26.352Z",
            "pageSize": 48,
            "page": 8,
            "gigId": 125815918,
            "pos": 47,
            "type": "promoted_gigs",
            "is_fiverr_choice": false,
            "seller_name": "alimehdi242",
            "seller_country": "PK",
            "seller_level": "level_two_seller",
            "is_pro": false,
            "buying_review_rating_count": 713,
            "buying_review_rating": 4.9,
            "price_i": 150,
            "count": 757,
            "score": 4.992467,
            "choice_eligibilities": "ALGO_A",
            "listingQuery": "website development"
        }
    ]
}