{
    "listings": [
        {
            "memberSince": 1643955537,
            "responseTime": 1,
            "recentDelivery": 1740890260000,
            "ordersInQueue": 1,
            "order_duration_in_days": 9,
            "order_price_range_usd": "$100-$200",
            "comment": "The work is good, could be better, I ask him if he can make me a logo and told him the details i wanted but instead he delivered me AI logo generated images which i can do by myself for free so not happy about that but he did refund me for that service and as for the website, he delivered in a timely manner but not as good as i thought it would be, overall I'm satisfied but the work could be better. ",
            "reviewer_country_code": "CA",
            "created_at": "2025-01-19T03:50:32",
            "value": 3,
            "score": 0.87951446,
            "repeat_buyer": false,
            "is_business": false,
            "gig_id": 242877184,
            "relevancy_score": 0.5,
            "reviews_count_as_buyer": 3,
            "is_cancelled_order": false
        },
        {
            "memberSince": 1643955537,
            "responseTime": 1,
            "recentDelivery": 1740890260000,
            "ordersInQueue": 1,
            "order_duration_in_days": 12,
            "order_price_range_usd": "$100-$200",
            "comment": "it was amazing working with Rajan. He understood our needs and made it an amazing website, we loved it. we recommend him to the people who want something amazing for their websites! best wishes for him, we will be working with him for a long time, thanks Rajan.",
            "reviewer_country_code": "BD",
            "created_at": "2025-01-16T07:15:51",
            "value": 5,
            "score": 0.7681879,
            "repeat_buyer": false,
            "is_business": false,
            "gig_id": 242877184,
            "relevancy_score": 1,
            "reviews_count_as_buyer": 8,
            "is_cancelled_order": false
        },
        {
            "memberSince": 1643955537,
            "responseTime": 1,
            "recentDelivery": 1740890260000,
            "ordersInQueue": 1,
            "order_duration_in_days": 2,
            "order_price_range_usd": "$50-$100",
            "comment": "Great work!! Rajan is very professional and extremely knowledgeable, He did everything, As per my requirement he customized my Shopify Store and also optimized the speed of my Shopify store. I will use Rajan again for my future work. I appreciate and recommend your service",
            "reviewer_country_code": "DK",
            "created_at": "2025-02-20T08:32:38",
            "value": 5,
            "score": 0.4994666,
            "repeat_buyer": false,
            "is_business": false,
            "gig_id": 242877184,
            "relevancy_score": 0.5,
            "reviews_count_as_buyer": 67,
            "is_cancelled_order": false
        },
        {
            "memberSince": 1643955537,
            "responseTime": 1,
            "recentDelivery": 1740890260000,
            "ordersInQueue": 1,
            "order_duration_in_days": 22,
            "order_price_range_usd": "$100-$200",
            "comment": "Pleased with the work completed by the designer. We had a few reviews which he corrected quickly. We will use his services in the future.",
            "reviewer_country_code": "GB",
            "created_at": "2024-12-20T19:52:04",
            "value": 5,
            "score": 0.30033123,
            "repeat_buyer": false,
            "is_business": true,
            "gig_id": 242877184,
            "relevancy_score": 0.5,
            "reviews_count_as_buyer": 42,
            "is_cancelled_order": false
        },
        {
            "memberSince": 1643955537,
            "responseTime": 1,
            "recentDelivery": 1740890260000,
            "ordersInQueue": 1,
            "order_duration_in_days": 3,
            "order_price_range_usd": "$50-$100",
            "comment": "Rajan is always a pleasure to work with. Good communication, high quality work which is done in a timely manner. Thanks Rajan",
            "reviewer_country_code": "US",
            "created_at": "2025-02-22T14:53:16",
            "value": 5,
            "score": 0.2539876,
            "repeat_buyer": true,
            "is_business": false,
            "gig_id": 242877184,
            "relevancy_score": 0.5,
            "reviews_count_as_buyer": 122,
            "is_cancelled_order": false
        }
    ]
}