{
  "general": {
    "gigId": 399103360,
    "gigStatus": "approved",
    "categoryId": 10,
    "categoryName": "Programming & Tech",
    "categorySlug": "programming-tech",
    "subCategoryId": 514,
    "subCategoryName": "Website Development",
    "subCategorySlug": "website-development",
    "nestedSubCategoryId": 2609,
    "nestedSubCategorySlug": "wordpress-development",
    "isOnVacation": false,
    "isBuyerBlocked": false,
    "isPro": false,
    "isHandpicked": false,
    "isStudio": false,
    "gigTitle": "do wordpress website design and website development",
    "encryptedGigId": "FG25F2756002",
    "sellerId": 174093155,
    "traffiqed": false,
    "isSellerBlocked": false,
    "gigVisibleToSeller": true,
    "gigVisibleToBuyer": true,
    "isTrustedUser": false,
    "includeWorkSample": true
  },
  "rollouts": {
    "anacondas_gig_page_request_to_order": true,
    "caribou_gig_report_eligibility": false,
    "cham_gig_page_lazy_load_pcp": false,
    "cobras_gig_returning_buyer_modal": false,
    "hawks_fiverr_ai_entry_points": true,
    "hawks_fiverr_ai_gig_page": true,
    "hawks_gig_page_is_dsa_applied": true,
    "lions_default_mt_translation": true,
    "lions_local_reviews_new": false,
    "panthers_post_fmp_more_gigs_v_four": false,
    "piglets_gig_page_paypal_paylater_message": false,
    "pro_launch_master": true,
    "qualas_gig_page_work_samples": true,
    "qualas_new_level_system_consumers_migration": true,
    "qualas_search_on_review_active": true,
    "qual_gig_page_seller_reviews_feature_flag": false,
    "starlings_boosting_new_gigs": false,
    "vipers_contact_drawer_entry": true,
    "zebras_acq_collection_stepper_gig_page": false,
    "zebras_create_ai_brief_on_gig_page": true,
    "zebras_hourly_rate": true,
    "zebras_seller_hourly_eligibility": true,
    "starlings_fiverr_go_floating_chat": false,
    "dsa_compliance_for_eu_consumers": true,
    "foxes_gig_page_render_delay_message": false
  },
  "outOfOffice": {
    "username": "qandeel_zahra1",
    "sellerId": 174093155,
    "isOnVacation": false,
    "endDate": null,
    "profilePhoto": "https://fiverr-res.cloudinary.com/image/upload/t_profile_original,q_auto,f_auto/v1/attachments/profile/photo/758aa8372fd65260eb0f250cb2e09ddf-1715861002319/f328ba62-6c8b-40d9-89cc-4d4b8862a2e3.jpeg",
    "allowContact": true,
    "awayReason": null,
    "awayMessage": null,
    "gigId": 399103360
  },
  "sellerCard": {
    "oneLiner": null,
    "rating": null,
    "achievement": 2,
    "ratingsCount": 44,
    "countryCode": "PK",
    "proficientLanguages": [
      {
        "name": "en",
        "level": 4
      }
    ],
    "memberSince": 1713535609,
    "responseTime": 1,
    "recentDelivery": 1740827965000,
    "description": "🚀 Welcome to Your Custom WordPress Website Solution! 🌍\r\n\r\n🔍 Struggling to make your business stand out online? Want a modern, responsive, and professional WordPress website that captivates your audience and drives results? You’re in the right place! Let’s create a website that sets you apart and boosts your online presence!",
    "isPro": false,
    "proSubCategories": [],
    "hasProfilePhoto": true,
    "profilePhoto": "https://fiverr-res.cloudinary.com/image/upload/t_profile_original,q_auto,f_auto/v1/attachments/profile/photo/758aa8372fd65260eb0f250cb2e09ddf-1715861002319/f328ba62-6c8b-40d9-89cc-4d4b8862a2e3.jpeg"
  },
  "description": {
    "content": "<p><strong>Professional, optimized, and fully responsive custom WordPress website</strong> needed for your business?</p><p>If so, you've come to the right place!</p><p>I specialize in designing and developing high-quality WordPress websites that are responsive across all devices desktops, tablets, and smartphones. Whether you have a concept in mind or need a fresh start, Ill create a secure, SEO-friendly, modern, and interactive WordPress site that reflects your vision.</p><p><strong>Lets collaborate to elevate your online presence!</strong></p><p><br></p><p><strong>Heres what youll get:</strong></p><ul><li><br></li><li>Responsive WordPress Website Design</li><li>Custom WordPress Development</li><li>Modern, Professional, and Responsive Layouts</li><li>Fully Functional Ecommerce Integration</li><li>Security, SEO, and Speed Optimization</li><li>Visually Appealing Design</li></ul><p><br></p><p><br></p><p><strong>Note:</strong> Please make sure to discuss your requirements with me before placing an order.</p><p><br></p><p><br></p><p>Thank you &amp; best regards</p><p>Qandeel Zahra</p><p><br></p><p><br></p><p><br></p>",
    "metadataAttributes": [
      {
        "name": "website_type",
        "options": [
          {
            "value": "business",
            "label": "Business"
          }
        ],
        "metadata": {
          "name": "website_type",
          "alias": "Website type",
          "translationKey": "metadata.category_2609.website_type.title",
          "visibility": "marketplace",
          "order": 10,
          "metadataOptions": {
            "e_commerce": {
              "name": "e_commerce",
              "alias": "E-Commerce store",
              "translationKey": "metadata.category_2609.website_type.options.e_commerce",
              "order": 10
            },
            "business": {
              "name": "business",
              "alias": "Business",
              "translationKey": "metadata.category_2609.website_type.options.business",
              "order": 20
            },
            "landing_page": {
              "name": "landing_page",
              "alias": "Landing page",
              "translationKey": "metadata.category_2609.website_type.options.landing_page",
              "order": 30
            },
            "blog": {
              "name": "blog",
              "alias": "Blog",
              "translationKey": "metadata.category_2609.website_type.options.blog",
              "order": 40
            },
            "education": {
              "name": "education",
              "alias": "Education",
              "translationKey": "metadata.category_2609.website_type.options.education",
              "order": 50
            },
            "portfolio": {
              "name": "portfolio",
              "alias": "Portfolio",
              "translationKey": "metadata.category_2609.website_type.options.portfolio",
              "order": 60
            },
            "entertainment": {
              "name": "entertainment",
              "alias": "Entertainment",
              "translationKey": "metadata.category_2609.website_type.options.entertainment",
              "order": 70
            },
            "nonprofit": {
              "name": "nonprofit",
              "alias": "Nonprofit",
              "translationKey": "metadata.category_2609.website_type.options.nonprofit",
              "order": 80
            },
            "wedding": {
              "name": "wedding",
              "alias": "Wedding",
              "translationKey": "metadata.category_2609.website_type.options.wedding",
              "order": 90
            },
            "podcasting": {
              "name": "podcasting",
              "alias": "Podcasting",
              "translationKey": "metadata.category_2609.website_type.options.podcasting",
              "order": 100
            },
            "online_communities": {
              "name": "online_communities",
              "alias": "Online communities",
              "translationKey": "metadata.category_2609.website_type.options.online_communities",
              "order": 110
            },
            "forms": {
              "name": "forms",
              "alias": "Forms",
              "translationKey": "metadata.category_2609.website_type.options.forms",
              "order": 120
            },
            "crowdfunding": {
              "name": "crowdfunding",
              "alias": "Crowdfunding",
              "translationKey": "metadata.category_2609.website_type.options.crowdfunding",
              "order": 130
            },
            "wiki_knowledge": {
              "name": "wiki_knowledge",
              "alias": "Wiki/Knowledge",
              "translationKey": "metadata.category_2609.website_type.options.wiki_knowledge",
              "order": 140
            },
            "saas": {
              "name": "saas",
              "alias": "Saas",
              "translationKey": "metadata.category_2609.website_type.options.saas",
              "order": 150
            },
            "job_board": {
              "name": "job_board",
              "alias": "Job board",
              "translationKey": "metadata.category_2609.website_type.options.job_board",
              "order": 160
            },
            "portal": {
              "name": "portal",
              "alias": "Portal",
              "translationKey": "metadata.category_2609.website_type.options.portal",
              "order": 170
            },
            "brochure": {
              "name": "brochure",
              "alias": "Brochure",
              "translationKey": "metadata.category_2609.website_type.options.brochure",
              "order": 180
            },
            "dropshipping": {
              "name": "dropshipping",
              "alias": "Dropshipping",
              "translationKey": "metadata.category_2609.website_type.options.dropshipping",
              "order": 190
            }
          },
          "label": "Website type"
        }
      },
      {
        "name": "website_features",
        "options": [
          {
            "value": "marketing",
            "label": "Marketing"
          },
          {
            "value": "video",
            "label": "Video"
          },
          {
            "value": "form",
            "label": "Form"
          },
          {
            "value": "events",
            "label": "Events"
          },
          {
            "value": "membership",
            "label": "Membership"
          },
          {
            "value": "map",
            "label": "Map"
          },
          {
            "value": "faq",
            "label": "FAQ"
          },
          {
            "value": "gallery",
            "label": "Gallery"
          },
          {
            "value": "booking",
            "label": "Booking"
          },
          {
            "value": "blog",
            "label": "Blog"
          }
        ],
        "metadata": {
          "name": "website_features",
          "alias": "Website features",
          "translationKey": "metadata.category_2609.website_features.title",
          "visibility": "marketplace",
          "order": 20,
          "metadataOptions": {
            "marketing": {
              "name": "marketing",
              "alias": "Marketing",
              "translationKey": "metadata.category_2609.website_features.options.marketing",
              "order": 10
            },
            "payment": {
              "name": "payment",
              "alias": "Payment",
              "translationKey": "metadata.category_2609.website_features.options.payment",
              "order": 20
            },
            "forum": {
              "name": "forum",
              "alias": "Forum",
              "translationKey": "metadata.category_2609.website_features.options.forum",
              "order": 30
            },
            "social_media": {
              "name": "social_media",
              "alias": "Social media",
              "translationKey": "metadata.category_2609.website_features.options.social_media",
              "order": 40
            },
            "customer_support": {
              "name": "customer_support",
              "alias": "Customer support",
              "translationKey": "metadata.category_2609.website_features.options.customer_support",
              "order": 50
            },
            "shipping": {
              "name": "shipping",
              "alias": "Shipping",
              "translationKey": "metadata.category_2609.website_features.options.shipping",
              "order": 60
            },
            "inventory": {
              "name": "inventory",
              "alias": "Inventory",
              "translationKey": "metadata.category_2609.website_features.options.inventory",
              "order": 70
            },
            "analytics": {
              "name": "analytics",
              "alias": "Analytics",
              "translationKey": "metadata.category_2609.website_features.options.analytics",
              "order": 80
            },
            "video": {
              "name": "video",
              "alias": "Video",
              "translationKey": "metadata.category_2609.website_features.options.video",
              "order": 90
            },
            "form": {
              "name": "form",
              "alias": "Form",
              "translationKey": "metadata.category_2609.website_features.options.form",
              "order": 100
            },
            "events": {
              "name": "events",
              "alias": "Events",
              "translationKey": "metadata.category_2609.website_features.options.events",
              "order": 110
            },
            "music": {
              "name": "music",
              "alias": "Music",
              "translationKey": "metadata.category_2609.website_features.options.music",
              "order": 120
            },
            "chat": {
              "name": "chat",
              "alias": "Chat",
              "translationKey": "metadata.category_2609.website_features.options.chat",
              "order": 130
            },
            "membership": {
              "name": "membership",
              "alias": "Membership",
              "translationKey": "metadata.category_2609.website_features.options.membership",
              "order": 140
            },
            "map": {
              "name": "map",
              "alias": "Map",
              "translationKey": "metadata.category_2609.website_features.options.map",
              "order": 150
            },
            "faq": {
              "name": "faq",
              "alias": "FAQ",
              "translationKey": "metadata.category_2609.website_features.options.faq",
              "order": 160
            },
            "gallery": {
              "name": "gallery",
              "alias": "Gallery",
              "translationKey": "metadata.category_2609.website_features.options.gallery",
              "order": 170
            },
            "booking": {
              "name": "booking",
              "alias": "Booking",
              "translationKey": "metadata.category_2609.website_features.options.booking",
              "order": 180
            },
            "calendar": {
              "name": "calendar",
              "alias": "Calendar",
              "translationKey": "metadata.category_2609.website_features.options.calendar",
              "order": 190
            },
            "blog": {
              "name": "blog",
              "alias": "Blog",
              "translationKey": "metadata.category_2609.website_features.options.blog",
              "order": 200
            },
            "other": {
              "name": "other",
              "alias": "Other",
              "translationKey": "metadata.category_2609.website_features.options.other",
              "order": 210
            }
          },
          "label": "Website features"
        }
      }
    ]
  },
  "gallery": {
    "slides": [
      {
        "slide": {
          "name": "do wordpress website design and website development",
          "src": "https://fiverr-res.cloudinary.com/images/t_main1,q_auto,f_auto,q_auto,f_auto/gigs/399103360/original/e7893aed70c349d62a53835a2dad0595c7ee16be/do-wordpress-website-design-and-website-development.png",
          "media": {
            "small": "https://fiverr-res.cloudinary.com/images/t_thumbnail3_3,q_auto,f_auto/gigs/399103360/original/e7893aed70c349d62a53835a2dad0595c7ee16be/do-wordpress-website-design-and-website-development.png",
            "medium": "https://fiverr-res.cloudinary.com/images/t_main1,q_auto,f_auto,q_auto,f_auto/gigs/399103360/original/e7893aed70c349d62a53835a2dad0595c7ee16be/do-wordpress-website-design-and-website-development.png",
            "original": "https://fiverr-res.cloudinary.com/images/q_auto,f_auto/gigs/399103360/original/e7893aed70c349d62a53835a2dad0595c7ee16be/do-wordpress-website-design-and-website-development.png"
          },
          "thumbnail": "https://fiverr-res.cloudinary.com/images/t_thumbnail3_3,q_auto,f_auto/gigs/399103360/original/e7893aed70c349d62a53835a2dad0595c7ee16be/do-wordpress-website-design-and-website-development.png",
          "isWorkSample": false,
          "itemScopeType": "ImageSlide",
          "attachmentId": "399103360_1",
          "typeImage": true,
          "filename": "e7893aed70c349d62a53835a2dad0595c7ee16be.png"
        }
      }
    ]
  },
  "faq": {
    "questionsAndAnswers": []
  },
  "packages": {
    "packageList": [
      {
        "id": 1,
        "title": "BASIC",
        "description": "Landing page, Home Page, Upto 3 sections",
        "price": 10000,
        "duration": 72,
        "maxNumWordsPerOneMoreDay": null,
        "maxNumWordsPerPackageDuration": null,
        "revisions": {
          "id": 399103691,
          "name": "modifications",
          "included": true,
          "value": 3,
          "price": 0,
          "extra": 3
        },
        "extraFast": {
          "id": 399103699,
          "name": "extra_fast",
          "included": false,
          "duration": 24,
          "value": 0,
          "price": 20000,
          "isPopular": false
        },
        "features": [
          {
            "id": 399103689,
            "name": "functional_website",
            "duration": 0,
            "included": true,
            "label": "Functional website",
            "value": 0,
            "extra": 0,
            "price": 0,
            "serviceId": null,
            "type": "BOOLEAN",
            "isPopular": false
          },
          {
            "id": 399103690,
            "name": "number_of_pages",
            "duration": 0,
            "included": true,
            "label": "Number of pages",
            "value": 1,
            "extra": 1,
            "price": 0,
            "serviceId": null,
            "type": "NUMERIC",
            "isPopular": false
          }
        ],
        "calculators": [],
        "customExtras": []
      },
      {
        "id": 2,
        "title": "STANDARD",
        "description": "Upto 3 pages including Home, About Us, Contact Us",
        "price": 25000,
        "duration": 168,
        "maxNumWordsPerOneMoreDay": null,
        "maxNumWordsPerPackageDuration": null,
        "revisions": {
          "id": 399103691,
          "name": "modifications",
          "included": true,
          "value": 3,
          "price": 0,
          "extra": 3
        },
        "extraFast": {
          "id": 399103699,
          "name": "extra_fast",
          "included": false,
          "duration": 72,
          "value": 0,
          "price": 20000,
          "isPopular": false
        },
        "features": [
          {
            "id": 399103689,
            "name": "functional_website",
            "duration": 0,
            "included": true,
            "label": "Functional website",
            "value": 0,
            "extra": 0,
            "price": 0,
            "serviceId": null,
            "type": "BOOLEAN",
            "isPopular": false
          },
          {
            "id": 399103690,
            "name": "number_of_pages",
            "duration": 0,
            "included": true,
            "label": "Number of pages",
            "value": 3,
            "extra": 3,
            "price": 0,
            "serviceId": null,
            "type": "NUMERIC",
            "isPopular": false
          },
          {
            "id": 399103692,
            "name": "responsive_design",
            "duration": 0,
            "included": true,
            "label": "Responsive design",
            "value": 0,
            "extra": 0,
            "price": 0,
            "serviceId": null,
            "type": "BOOLEAN",
            "isPopular": false
          },
          {
            "id": 399103698,
            "name": "social_media_icons",
            "duration": 0,
            "included": true,
            "label": "Social media icons",
            "value": 0,
            "extra": 0,
            "price": 0,
            "serviceId": null,
            "type": "BOOLEAN",
            "isPopular": false
          }
        ],
        "calculators": [],
        "customExtras": []
      },
      {
        "id": 3,
        "title": "PREMIUM",
        "description": "Upto 5 pages including everything",
        "price": 50000,
        "duration": 240,
        "maxNumWordsPerOneMoreDay": null,
        "maxNumWordsPerPackageDuration": null,
        "revisions": {
          "id": 399103691,
          "name": "modifications",
          "included": true,
          "value": -1,
          "price": 0,
          "extra": -1
        },
        "extraFast": {
          "id": 399103699,
          "name": "extra_fast",
          "included": false,
          "duration": 120,
          "value": 0,
          "price": 20000,
          "isPopular": false
        },
        "features": [
          {
            "id": 399103689,
            "name": "functional_website",
            "duration": 0,
            "included": true,
            "label": "Functional website",
            "value": 0,
            "extra": 0,
            "price": 0,
            "serviceId": null,
            "type": "BOOLEAN",
            "isPopular": false
          },
          {
            "id": 399103690,
            "name": "number_of_pages",
            "duration": 0,
            "included": true,
            "label": "Number of pages",
            "value": 5,
            "extra": 5,
            "price": 0,
            "serviceId": null,
            "type": "NUMERIC",
            "isPopular": false
          },
          {
            "id": 399103692,
            "name": "responsive_design",
            "duration": 0,
            "included": true,
            "label": "Responsive design",
            "value": 0,
            "extra": 0,
            "price": 0,
            "serviceId": null,
            "type": "BOOLEAN",
            "isPopular": false
          },
          {
            "id": 399103693,
            "name": "content_upload",
            "duration": 0,
            "included": true,
            "label": "Content upload",
            "value": 0,
            "extra": 0,
            "price": 0,
            "serviceId": null,
            "type": "BOOLEAN",
            "isPopular": false
          },
          {
            "id": 399103694,
            "name": "e_commerce_functionality",
            "duration": 0,
            "included": true,
            "label": "E-commerce functionality",
            "value": 0,
            "extra": 0,
            "price": 0,
            "serviceId": null,
            "type": "BOOLEAN",
            "isPopular": false
          },
          {
            "id": 399103695,
            "name": "number_of_products",
            "duration": 0,
            "included": true,
            "label": "Number of products",
            "value": 3,
            "extra": 3,
            "price": 0,
            "serviceId": null,
            "type": "NUMERIC",
            "isPopular": false
          },
          {
            "id": 399103696,
            "name": "payment_processing",
            "duration": 0,
            "included": true,
            "label": "Payment Integration",
            "value": 0,
            "extra": 0,
            "price": 0,
            "serviceId": null,
            "type": "BOOLEAN",
            "isPopular": false
          },
          {
            "id": 399103697,
            "name": "speed_optimization",
            "duration": 0,
            "included": true,
            "label": "Speed optimization",
            "value": 0,
            "extra": 0,
            "price": 0,
            "serviceId": null,
            "type": "BOOLEAN",
            "isPopular": false
          },
          {
            "id": 399103698,
            "name": "social_media_icons",
            "duration": 0,
            "included": true,
            "label": "Social media icons",
            "value": 0,
            "extra": 0,
            "price": 0,
            "serviceId": null,
            "type": "BOOLEAN",
            "isPopular": false
          }
        ],
        "calculators": [],
        "customExtras": []
      }
    ],
    "recurringOptions": []
  },
  "tags": {
    "tagsGigList": [
      {
        "name": "wordpress developer",
        "slug": "wordpress-developer",
        "formattedClassification": {
          "type": "customUrl",
          "key": "categories/programming-tech/website-development/wordpress-development"
        }
      },
      {
        "name": "build website",
        "slug": "build-website",
        "formattedClassification": {
          "type": "differentTag",
          "key": "website"
        }
      },
      {
        "name": "website design",
        "slug": "website-design",
        "formattedClassification": {
          "type": "subCategory",
          "key": {
            "categorySlug": "graphics-design",
            "subCategorySlug": "website-design"
          }
        }
      },
      {
        "name": "website development",
        "slug": "website-development",
        "formattedClassification": {
          "type": "subCategory",
          "key": {
            "categorySlug": "programming-tech",
            "subCategorySlug": "website-development"
          }
        }
      },
      {
        "name": "wordpress website",
        "slug": "wordpress-website",
        "formattedClassification": {
          "type": "customUrl",
          "key": "categories/programming-tech/website-development/wordpress-development"
        }
      }
    ]
  },
  "overview": {
    "gig": {
      "id": 399103360,
      "title": "do wordpress website design and website development",
      "rating": 5,
      "ratingsCount": 44,
      "ordersInQueue": 10
    },
    "seller": {
      "id": 174093155,
      "username": "qandeel_zahra1",
      "achievement": null,
      "isPro": false,
      "hasProfilePhoto": true,
      "profilePhoto": "https://fiverr-res.cloudinary.com/image/upload/t_profile_original,q_auto,f_auto/v1/attachments/profile/photo/758aa8372fd65260eb0f250cb2e09ddf-1715861002319/f328ba62-6c8b-40d9-89cc-4d4b8862a2e3.jpeg",
      "countryCode": "PK",
      "proficientLanguages": [
        {
          "name": "en",
          "level": 4
        }
      ]
    },
    "categories": {
      "category": {
        "name": "Programming & Tech",
        "slug": "programming-tech"
      },
      "subCategory": {
        "name": "Website Development",
        "slug": "website-development"
      },
      "nestedSubCategory": {
        "name": "WordPress",
        "slug": "wordpress-development"
      }
    }
  },
  "pro": {
    "isPro": false
  },
  "topNav": {
    "gigId": 399103360,
    "gigTitle": "do wordpress website design and website development",
    "gigCollectedCount": 64,
    "sellerId": 174093155,
    "sellerName": "qandeel_zahra1"
  },
  "portfolio": {
    "slug": "do-wordpress-website-design-and-website-development",
    "username": "qandeel_zahra1",
    "projectsCount": 0,
    "nextProjectIds": [],
    "portfolioProjects": [],
    "portfolioProjectsThumbs": []
  },
  "seo": {
    "title": {
      "gigTitle": "do wordpress website design and website development",
      "sellerUsername": "qandeel_zahra1"
    },
    "description": {
      "sellerAchievement": "",
      "subCategoryName": "Website Development",
      "gigTitle": "do wordpress website design and website development",
      "serviceInclude": "Functional website",
      "deliveryTime": "3 days"
    },
    "schemaMarkup": {
      "type": "Product",
      "gigTitle": "do wordpress website design and website development",
      "gigImage": "https://fiverr-res.cloudinary.com/images/t_main1,q_auto,f_auto,q_auto,f_auto/gigs/399103360/original/e7893aed70c349d62a53835a2dad0595c7ee16be/do-wordpress-website-design-and-website-development.png",
      "gigRatings": {
        "type": "AggregateRating",
        "value": "1.7",
        "count": "44",
        "best": "5",
        "worst": "0"
      },
      "gigOffers": {
        "type": "AggregateOffer",
        "lowPrice": "100.00",
        "highPrice": "500.00",
        "currency": "USD",
        "availability": "inStock"
      }
    }
  },
  "customOrder": {
    "seller": {
      "status": "active",
      "isOnVacation": false
    },
    "gig": {
      "status": "approved",
      "categoryId": 10,
      "subCategoryId": 514
    },
    "currentUserStatus": null,
    "allowCustomOrders": true,
    "responseTime": 1
  },
  "moreServices": {
    "subCategoryName": "Website Development",
    "otherNestedSubCategoryGigs": []
  },
  "otherGigs": {
    "gigIds": []
  },
  "openGraph": {
    "description": "<p><strong>Professional, optimized, and fully responsive custom WordPress website</strong> needed for your business?</p><p>If so, you've come to the right place!</p><p>I specialize in designing and developing high-quality WordPress websites that are responsive across all devices desktops, tablets, and smartphones. Whether you have a concept in mind or need a fresh start, Ill create a secure, SEO-friendly, modern, and interactive WordPress site that reflects your vision.</p><p><strong>Lets collaborate to elevate your online presence!</strong></p><p><br></p><p><strong>Heres what youll get:</strong></p><ul><li><br></li><li>Responsive WordPress Website Design</li><li>Custom WordPress Development</li><li>Modern, Professional, and Responsive Layouts</li><li>Fully Functional Ecommerce Integration</li><li>Security, SEO, and Speed Optimization</li><li>Visually Appealing Design</li></ul><p><br></p><p><br></p><p><strong>Note:</strong> Please make sure to discuss your requirements with me before placing an order.</p><p><br></p><p><br></p><p>Thank you &amp; best regards</p><p>Qandeel Zahra</p><p><br></p><p><br></p><p><br></p>",
    "title": "do wordpress website design and website development",
    "price": 10000,
    "image": "https://fiverr-res.cloudinary.com/images/t_main1,q_auto,f_auto,q_auto,f_auto/gigs/399103360/original/e7893aed70c349d62a53835a2dad0595c7ee16be/do-wordpress-website-design-and-website-development.png",
    "video": null
  },
  "choiceEligibilities": [
    {
      "type": "ALGO_A"
    }
  ],
  "repeatScore": {},
  "workflow": {},
  "workProcess": {},
  "instantOrderSettings": [],
  "promotedGigs": [],
  "highlightsData": {},
  "reviews": {
    "has_next": true,
    "rating_algo_type": 1,
    "gig_id": 399103360,
    "average_valuation": 5,
    "total_count": 44,
    "reviews": [
      {
        "order_duration": "1 day",
        "order_duration_en": "1 day",
        "order_duration_in_days": 1,
        "order_price_range": "PKR112,000-PKR168,000",
        "order_price_range_usd": "$400-$600",
        "id": "67a67a7ff89f595e7a4cd024",
        "comment": "Wow! This website exceeded my expectations. Everything from the homepage to the car details page is perfectly designed. The seller was super helpful and professional throughout the process. Highly recommend to anyone looking for a quality website!",
        "comment_language": "en",
        "username": "nathangeorge36",
        "reviewer_country_code": "US",
        "user_image_url": "https://fiverr-res.cloudinary.com/image/upload/f_auto,q_auto,t_profile_small/v1/attachments/profile/photo/8495ea5a237f622232dc0de0b4e759fe-1738957489945/7314a2c2-0edd-459a-b71a-af200f99441b.jpg",
        "created_at": "2025-02-07T21:48:52",
        "value": 5,
        "reviewer_country": "United States",
        "encrypted_order_id": "FO319F4C33D85",
        "score": 0.5960724,
        "reviewer_industry": [],
        "repeat_buyer": false,
        "is_business": false,
        "gig_id": 399103360,
        "relevancy_score": 0.5,
        "price_range_start": 10000,
        "reviews_count_as_buyer": 1,
        "is_cancelled_order": false,
        "original_relevancy_score": 0.5
      },
      {
        "order_duration": "1 day",
        "order_duration_en": "1 day",
        "order_duration_in_days": 1,
        "order_price_range": "PKR112,000-PKR168,000",
        "order_price_range_usd": "$400-$600",
        "id": "6799e179bd3fd9607c3de1fd",
        "comment": "\"Faintest Work\" is a masterpiece that blends creativity and precision effortlessly. The attention to detail and the level of craftsmanship put into it are truly remarkable. From the very first interaction, it’s clear that a lot of thought and expertise have gone into this work. The execution is flawless, with a seamless flow that keeps you engaged throughout. I highly recommend it to anyone looking for top-quality results. Absolutely worth it!",
        "comment_language": "en",
        "username": "sophiagrace36",
        "reviewer_country_code": "US",
        "user_image_url": "https://fiverr-res.cloudinary.com/image/upload/f_auto,q_auto,t_profile_small/v1/attachments/profile/photo/3aa0daf9709c7a736bd7c9d96905d4fb-1738087016995/a75e4d96-4cd3-4ae9-818c-eddfa59c85cd.jpg",
        "created_at": "2025-01-29T08:41:30",
        "value": 5,
        "reviewer_country": "United States",
        "encrypted_order_id": "FO5136D802CC1",
        "score": 0.5919358,
        "reviewer_industry": [],
        "repeat_buyer": false,
        "is_business": false,
        "gig_id": 399103360,
        "relevancy_score": 0.5,
        "price_range_start": 10000,
        "reviews_count_as_buyer": 1,
        "is_cancelled_order": false,
        "original_relevancy_score": 0.5
      },
      {
        "order_duration": "8 days",
        "order_duration_en": "8 days",
        "order_duration_in_days": 8,
        "order_price_range": "PKR28,000-PKR56,000",
        "order_price_range_usd": "$100-$200",
        "id": "67c0ef2af61cc60288a872f2",
        "comment": "I was very pleased. I wasn't sure what I wanted. I was guided as to how I might access a source that could help me with that. I didn't have any problems when I didn't like something and wanted something completely opposite. It turned out very well. I was glad we worked together.",
        "comment_language": "en",
        "username": "jim_copell",
        "reviewer_country_code": "US",
        "created_at": "2025-02-28T01:46:35",
        "value": 5,
        "reviewer_country": "United States",
        "encrypted_order_id": "FO1D023CB743",
        "score": 0.45947433,
        "reviewer_industry": [],
        "repeat_buyer": false,
        "is_business": false,
        "gig_id": 399103360,
        "relevancy_score": 0.5,
        "price_range_start": 10000,
        "reviews_count_as_buyer": 1,
        "is_cancelled_order": false,
        "original_relevancy_score": 0.5
      },
      {
        "order_duration": "1 day",
        "order_duration_en": "1 day",
        "order_duration_in_days": 1,
        "order_price_range": "PKR112,000-PKR168,000",
        "order_price_range_usd": "$400-$600",
        "id": "679f37d1ddae5266e92d3326",
        "comment": "Qandeel  truly IMPRESSED with top-tier documentation and exceptional code expertise. The professionalism in their work is unmatched, making collaboration a breeze with proactive communication and quick responses. A fantastic experience overall in website development! 👍",
        "comment_language": "en",
        "username": "miaelizabeth36",
        "reviewer_country_code": "US",
        "user_image_url": "https://fiverr-res.cloudinary.com/image/upload/f_auto,q_auto,t_profile_small/v1/attachments/profile/photo/4bda1245bcf15a207be2d54e27ca1787-1738431321995/365392fa-feae-4036-b87d-e5a5012e810a.jpg",
        "created_at": "2025-02-02T09:37:21",
        "value": 5,
        "reviewer_country": "United States",
        "encrypted_order_id": "FO526E2D0BCC7",
        "score": 0.42210898,
        "reviewer_industry": [],
        "repeat_buyer": false,
        "is_business": false,
        "gig_id": 399103360,
        "relevancy_score": 0.5,
        "price_range_start": 10000,
        "reviews_count_as_buyer": 1,
        "is_cancelled_order": false,
        "original_relevancy_score": 0.5
      },
      {
        "order_duration": "1 day",
        "order_duration_en": "1 day",
        "order_duration_in_days": 1,
        "order_price_range": "PKR56,000-PKR112,000",
        "order_price_range_usd": "$200-$400",
        "id": "679ba94ec7be6a1c0ce2d106",
        "comment": "Qandeel is a top-notch WEBSITE DEVELOPER who consistently exceeded expectations with bug-free and expertly written code. Their LANGUAGE FLUENCY and cooperative spirit made the collaboration seamless, and they truly went above and beyond. I'm very happy with their work — Qandeel, you are a GREAT seller! 👏",
        "comment_language": "en",
        "username": "elijahhenry62",
        "reviewer_country_code": "US",
        "user_image_url": "https://fiverr-res.cloudinary.com/image/upload/f_auto,q_auto,t_profile_small/v1/attachments/profile/photo/ab7ffd9329eef50ea261f8ec07e40b83-1738182167992/95364572-6a0e-4046-9350-484059c7edb1.jpg",
        "created_at": "2025-01-30T17:56:16",
        "value": 5,
        "reviewer_country": "United States",
        "encrypted_order_id": "FO519E8F01183",
        "score": 0.41626516,
        "reviewer_industry": [],
        "repeat_buyer": false,
        "is_business": false,
        "gig_id": 399103360,
        "relevancy_score": 0.5,
        "price_range_start": 10000,
        "reviews_count_as_buyer": 1,
        "is_cancelled_order": false,
        "original_relevancy_score": 0.5
      }
    ],
    "reviews_snippet": [
      {
        "id": "67a67a7ff89f595e7a4cd024",
        "comment": "Wow! This website exceeded my expectations. Everything from the homepage to the car details page is perfectly designed. The seller was super helpful and professional throughout the process. Highly recommend to anyone looking for a quality website!",
        "comment_language": "en",
        "username": "nathangeorge36",
        "reviewer_country_code": "US",
        "user_image_url": "https://fiverr-res.cloudinary.com/image/upload/f_auto,q_auto,t_profile_small/v1/attachments/profile/photo/8495ea5a237f622232dc0de0b4e759fe-1738957489945/7314a2c2-0edd-459a-b71a-af200f99441b.jpg",
        "created_at": "2025-02-07T21:48:52",
        "value": 5,
        "reviewer_country": "United States",
        "timestamp": 1738964932
      },
      {
        "id": "6799e179bd3fd9607c3de1fd",
        "comment": "\"Faintest Work\" is a masterpiece that blends creativity and precision effortlessly. The attention to detail and the level of craftsmanship put into it are truly remarkable. From the very first interaction, it’s clear that a lot of thought and expertise have gone into this work. The execution is flawless, with a seamless flow that keeps you engaged throughout. I highly recommend it to anyone looking for top-quality results. Absolutely worth it!",
        "comment_language": "en",
        "username": "sophiagrace36",
        "reviewer_country_code": "US",
        "user_image_url": "https://fiverr-res.cloudinary.com/image/upload/f_auto,q_auto,t_profile_small/v1/attachments/profile/photo/3aa0daf9709c7a736bd7c9d96905d4fb-1738087016995/a75e4d96-4cd3-4ae9-818c-eddfa59c85cd.jpg",
        "created_at": "2025-01-29T08:41:30",
        "value": 5,
        "reviewer_country": "United States",
        "timestamp": 1738140090
      },
      {
        "id": "67c0ef2af61cc60288a872f2",
        "comment": "I was very pleased. I wasn't sure what I wanted. I was guided as to how I might access a source that could help me with that. I didn't have any problems when I didn't like something and wanted something completely opposite. It turned out very well. I was glad we worked together.",
        "comment_language": "en",
        "username": "jim_copell",
        "reviewer_country_code": "US",
        "created_at": "2025-02-28T01:46:35",
        "value": 5,
        "reviewer_country": "United States",
        "timestamp": 1740707195
      },
      {
        "id": "679f37d1ddae5266e92d3326",
        "comment": "Qandeel  truly IMPRESSED with top-tier documentation and exceptional code expertise. The professionalism in their work is unmatched, making collaboration a breeze with proactive communication and quick responses. A fantastic experience overall in website development! 👍",
        "comment_language": "en",
        "username": "miaelizabeth36",
        "reviewer_country_code": "US",
        "user_image_url": "https://fiverr-res.cloudinary.com/image/upload/f_auto,q_auto,t_profile_small/v1/attachments/profile/photo/4bda1245bcf15a207be2d54e27ca1787-1738431321995/365392fa-feae-4036-b87d-e5a5012e810a.jpg",
        "created_at": "2025-02-02T09:37:21",
        "value": 5,
        "reviewer_country": "United States",
        "timestamp": 1738489041
      },
      {
        "id": "679ba94ec7be6a1c0ce2d106",
        "comment": "Qandeel is a top-notch WEBSITE DEVELOPER who consistently exceeded expectations with bug-free and expertly written code. Their LANGUAGE FLUENCY and cooperative spirit made the collaboration seamless, and they truly went above and beyond. I'm very happy with their work — Qandeel, you are a GREAT seller! 👏",
        "comment_language": "en",
        "username": "elijahhenry62",
        "reviewer_country_code": "US",
        "user_image_url": "https://fiverr-res.cloudinary.com/image/upload/f_auto,q_auto,t_profile_small/v1/attachments/profile/photo/ab7ffd9329eef50ea261f8ec07e40b83-1738182167992/95364572-6a0e-4046-9350-484059c7edb1.jpg",
        "created_at": "2025-01-30T17:56:16",
        "value": 5,
        "reviewer_country": "United States",
        "timestamp": 1738259776
      }
    ],
    "star_summary": {
      "communication_valuation": 5,
      "quality_of_delivery_valuation": 5,
      "value_for_money_valuation": 5
    },
    "breakdown": [
      {
        "average_valuation_value": 1,
        "count": 0
      },
      {
        "average_valuation_value": 2,
        "count": 0
      },
      {
        "average_valuation_value": 3,
        "count": 0
      },
      {
        "average_valuation_value": 4,
        "count": 0
      },
      {
        "average_valuation_value": 5,
        "count": 44
      }
    ],
    "seller_username": "qandeel_zahra1",
    "seller_img_url": "https://fiverr-res.cloudinary.com/image/upload/f_auto,q_auto,t_profile_small/v1/attachments/profile/photo/758aa8372fd65260eb0f250cb2e09ddf-1715861002319/f328ba62-6c8b-40d9-89cc-4d4b8862a2e3.jpeg",
    "filters_counters": {
      "work_sample": 0,
      "most_common_industries": {
        "media_or_entertainment": 4
      },
      "business": 0
    },
    "dynamicTranslations": {
      "media_or_entertainment": "Media & Entertainment"
    }
  },
  "notableClients": [],
  "isTrustedFreelancer": false,
  "gigTranslationsCacheFlagsValues": {
    "de-DE": true,
    "es": true,
    "fr-FR": true,
    "it-IT": true
  },
  "isFloatingChatEnabled": false,
  "seller": {
    "sellerLevel": "LEVEL_TWO",
    "isHighlyResponsive": true,
    "introVideo": {
      "url": null
    },
    "isVerified": false,
    "user": {
      "profile": {
        "displayName": "Qandeel Z"
      },
      "id": "174093155",
      "languages": [
        {
          "code": "EN"
        }
      ]
    },
    "activeStructuredSkills": [
      {
        "id": "617fa67d0565f07789006cef",
        "name": "WordPress",
        "level": "PRO",
        "label": "WordPress"
      },
      {
        "id": "617fa67b0565f07789006c85",
        "name": "Website development",
        "level": "PRO",
        "label": "Website development"
      },
      {
        "id": "617fa6540565f07789006113",
        "name": "Generic website",
        "level": "PRO",
        "label": "Generic website"
      },
      {
        "id": "617fa65b0565f07789006348",
        "name": "Install WordPress",
        "level": "PRO",
        "label": "Install WordPress"
      },
      {
        "id": "617fa67d0565f07789006cfc",
        "name": "Wordpress SEO",
        "level": "PRO",
        "label": "Wordpress SEO"
      },
      {
        "id": "617fa67d0565f07789006cf9",
        "name": "WordPress migration",
        "level": "PRO",
        "label": "WordPress migration"
      }
    ],
    "completedOrdersCount": 49,
    "courses": {
      "nodes": []
    },
    "certifications": [],
    "activeEducations": [],
    "isOnVacation": false,
    "vacation": null,
    "portfolios": {
      "totalCount": 0,
      "portfolioProjects": []
    },
    "rating": {
      "score": 5,
      "count": 44
    },
    "agency": null,
    "hourlyRate": null,
    "regionalGroupRestrictions": [],
    "hasLoyaltyScores": false,
    "isActive": true,
    "isPro": false
  },
  "gigSellerTranslation": {
    "isEnabled": false
  },
  "centralizedGig": {
    "status": "not_requested"
  },
  "consultationData": {},
  "aiModels": [],
  "sellerHourlyEligibility": {
    "sellerHourlyEligible": false
  },
  "isRestrictedPage": false,
  "regionCode": "PB",
  "currency": {
    "name": "PKR",
    "rate": 293.653575,
    "template": "₨{{amount}}",
    "forceRound": true,
    "forceRoundFromAmount": 0,
    "symbol": "₨"
  },
  "gigTheme": "experiential",
  "newProBanner": {
    "wasClosed": false
  }
}